qilowatt/__init__.py
qilowatt/base_device.py
qilowatt/client.py
qilowatt/constants.py
qilowatt/exceptions.py
qilowatt/models.py
qilowatt/devices/inverter.py
qilowatt/devices/power_switch.py
qilowatt/devices/switch.py
qilowatt/devices/thermostat.py
qilowatt-2025.12.1.dist-info/licenses/LICENSE.txt
qilowatt-2025.12.1.dist-info/METADATA
qilowatt-2025.12.1.dist-info/WHEEL
qilowatt-2025.12.1.dist-info/top_level.txt
qilowatt-2025.12.1.dist-info/RECORD
