Metadata-Version: 2.4
Name: qilowatt
Version: 2025.12.1
Summary: Communication package for Qilowatt inverters
Author-email: Tanel Vakker <tanel@vakker.org>
License: MIT
Project-URL: Homepage, https://github.com/qilowatt/qilowatt-py
Project-URL: Documentation, https://github.com/qilowatt/qilowatt-py#readme
Project-URL: Issues, https://github.com/qilowatt/qilowatt-py/issues
Project-URL: Repository, https://github.com/qilowatt/qilowatt-py
Keywords: mqtt,qilowatt,inverter,energy,home-assistant
Classifier: Development Status :: 4 - Beta
Classifier: Intended Audience :: Developers
Classifier: Topic :: Home Automation
Classifier: Topic :: Software Development :: Libraries
Classifier: License :: OSI Approved :: MIT License
Classifier: Programming Language :: Python :: 3
Classifier: Programming Language :: Python :: 3.7
Classifier: Programming Language :: Python :: 3.8
Classifier: Programming Language :: Python :: 3.9
Classifier: Programming Language :: Python :: 3.10
Classifier: Operating System :: OS Independent
Requires-Python: >=3.7
License-File: LICENSE.txt
Requires-Dist: paho-mqtt>=1.6.1
Requires-Dist: getmac>=0.8.3
Provides-Extra: dev
Requires-Dist: pytest>=7.0; extra == "dev"
Dynamic: license-file
